{"Configurations":{"pageFlipSound":{"forward":"page-flip-sound.mp3","backward":"page-flip-sound.mp3"},"pageFlipTransitionDuration":0.6,"paragraphTextFadeDuration":0.4,"autoplayPageTurnDelay":0.2,"autoplayKeyframeDelay":0.1,"homeMenuForPages":{"normalStateImage":"home.png","tappedStateImage":"home-over.png","position":[44,46]}},"Pages":[{"API":{"CCMoveTo":[{"actionTag":2,"duration":0,"position":[506,28]},{"actionTag":3,"duration":2,"position":[508,734]}],"CCScaleTo":[{"actionTag":1,"duration":0,"intensity":1.5}],"CCSequence":[],"CCDelayTime":[],"CCSpawn":[],"CCStorySwipeEnded":{"runAction":[{"runAfterSwipeNumber":1,"spriteTag":2,"actionTags":[3]}]},"CCSprites":[{"image":"b66d0b6dd27814e848b3d600cdb31fe5.jpg","spriteTag":2,"position":[506,28],"actions":[1,2]}]},"Page":{"settings":{"number":1},"text":{"paragraphs":[{"linesOfText":[{"text":"","xOffset":0,"yOffset":0,"fontType":"Arial.ttf","fontColor":[255,183,213],"fontHighlightColor":[255,0,0],"fontSize":25}],"hotspots":[{"glitterIndicator":true,"stopEffectIndicator":false,"touchFlag":1,"position":[173,543],"radius":118,"soundToPlay":"2132165ba1abced9000a47d98b7c6ec6.mp3"}],"highlightingTimes":[0],"voiceAudioFile":null},{"linesOfText":[{"text":"","xOffset":0,"yOffset":0,"fontType":"Arial.ttf","fontColor":[255,183,213],"fontHighlightColor":[255,0,0],"fontSize":25}],"hotspots":[{"glitterIndicator":true,"stopEffectIndicator":false,"touchFlag":1,"position":[888,146],"radius":144,"videoToPlay":"a6fb9583dab8b385b8f12f5946b0b390.mov"}],"highlightingTimes":[0],"voiceAudioFile":null}]}}}],"MainMenu":{"CCSprites":[{"image":"0330fc3cd5c5c43a3e759712f6f39af6.jpg","spriteTag":1,"position":[510,642],"visible":true}],"fallingPhysicsSettings":{"plistfilename":"snowflake-main-menu.plist"},"MenuItems":[{"normalStateImage":"read_it_myself.png","tappedStateImage":"read_it_myself-over.png","storyMode":"readItMyself","position":[200,100]},{"normalStateImage":"read_to_me.png","tappedStateImage":"read_to_me-over.png","storyMode":"readToMe","position":[200,200]},{"normalStateImage":"auto_play.png","tappedStateImage":"auto_play-over.png","storyMode":"autoPlay","position":[200,300]}],"API":{}}}